GeneralSQL/Error.py
GeneralSQL/LICENSE
GeneralSQL/README.md
GeneralSQL/__init__.py
GeneralSQL/Template/__init__.py
GeneralSQL/Template/base.py
GeneralSQL/db/Jmysql.py
GeneralSQL/db/Jsqlite3.py
GeneralSQL/db/__init__.py
GeneralSQL-1.4.2.dist-info/METADATA
GeneralSQL-1.4.2.dist-info/WHEEL
GeneralSQL-1.4.2.dist-info/top_level.txt
GeneralSQL-1.4.2.dist-info/RECORD
