Metadata-Version: 2.2
Name: GeneralSQL
Version: 1.4.2
Summary: Sql generator tool.
Author-email: joker-zzp <joker_zzp@qq.com>
License:                     GNU GENERAL PUBLIC LICENSE
Project-URL: Homepage, https://github.com/joker-zzp/GeneralSQL
Project-URL: Issues, https://github.com/joker-zzp/GeneralSQL/issues
Classifier: Programming Language :: Python :: 3
Classifier: License :: OSI Approved :: GNU General Public License v3 (GPLv3)
Classifier: Operating System :: OS Independent
Requires-Python: >=3.8
